secure_package/__init__.py
secure_package/secure_package.py
secure_package-0.1.0.dist-info/AUTHORS.rst
secure_package-0.1.0.dist-info/LICENSE
secure_package-0.1.0.dist-info/METADATA
secure_package-0.1.0.dist-info/WHEEL
secure_package-0.1.0.dist-info/top_level.txt
secure_package-0.1.0.dist-info/RECORD
