Metadata-Version: 2.1
Name: secure-package
Version: 0.1.0
Summary: Secure package, don't use it.
Home-page: https://github.com/yeisonvargasf/secure_package
Author: Yeison Vargas
Author-email: yeisonvargasjf@gmail.com
License: GNU General Public License v3
Keywords: secure_package
Classifier: Development Status :: 2 - Pre-Alpha
Classifier: Intended Audience :: Developers
Classifier: License :: OSI Approved :: GNU General Public License v3 (GPLv3)
Classifier: Natural Language :: English
Classifier: Programming Language :: Python :: 3
Classifier: Programming Language :: Python :: 3.6
Classifier: Programming Language :: Python :: 3.7
Classifier: Programming Language :: Python :: 3.8
Requires-Python: >=3.6
License-File: LICENSE
License-File: AUTHORS.rst
